pixel_forge-0.1.1.dist-info/METADATA
pixel_forge-0.1.1.dist-info/WHEEL
pixel_forge-0.1.1.dist-info/license_files/LICENSE
pixel_forge/__init__.py
pixel_forge/__init__.pyi
pixel_forge/py.typed
pixel_forge/pixel_forge.cp39-win_amd64.pyd
pixel_forge-0.1.1.dist-info/RECORD
