Metadata-Version: 2.3
Name: pixel_forge
Version: 0.1.1
Classifier: Intended Audience :: Developers
Classifier: License :: OSI Approved :: MIT License
Classifier: Operating System :: Microsoft :: Windows
Classifier: Programming Language :: Python
Classifier: Programming Language :: Python :: 3.8
Classifier: Programming Language :: Python :: 3.9
Classifier: Programming Language :: Python :: 3.10
Classifier: Programming Language :: Python :: 3.11
Classifier: Programming Language :: Python :: 3.12
Classifier: Programming Language :: Python :: 3 :: Only
Classifier: Programming Language :: Rust
Requires-Dist: numpy
Requires-Dist: pytest ; extra == 'test'
Provides-Extra: test
License-File: LICENSE
Summary: Ultra-fast screen capture in Rust with Python bindings
Keywords: screenshot,window,capture
Author-email: Martin Schuck <real.amacati@gmail.com>
Requires-Python: >=3.8.0
Project-URL: Repository, https://github.com/amacati/pixel_forge
Project-URL: Documentation, https://pixel-forge.readthedocs.io/en/latest
